INSTALL.rst
INSTALL.xml
MANIFEST.in
Makefile
NEWS.rst
NEWS.xml
README.rst
setup.cfg
setup.py
src/ll/__init__.py
src/ll/toxic.py
src/ll_toxic.egg-info/PKG-INFO
src/ll_toxic.egg-info/SOURCES.txt
src/ll_toxic.egg-info/dependency_links.txt
src/ll_toxic.egg-info/namespace_packages.txt
src/ll_toxic.egg-info/not-zip-safe
src/ll_toxic.egg-info/requires.txt
src/ll_toxic.egg-info/top_level.txt
test/test_toxic.py
